text_classifier_kv/__init__.py
text_classifier_kv-0.0.8.dist-info/LICENSE
text_classifier_kv-0.0.8.dist-info/METADATA
text_classifier_kv-0.0.8.dist-info/WHEEL
text_classifier_kv-0.0.8.dist-info/top_level.txt
text_classifier_kv-0.0.8.dist-info/RECORD
