Metadata-Version: 2.1
Name: text-classifier-kv
Version: 0.0.8
Summary: text classifier
Home-page: https://github.com/kopylovvlad/text_classifier_kv
Author: Vladislav Kopylov
Author-email: kopylov.vlad@gmail.com
License: UNKNOWN
Platform: UNKNOWN
Requires-Python: >=3.5
